[{"page_id":"143a94ce-1d13-80b3-8503-db45dd6fa8a9","classification":"행사","year":2024,"name":"Time for SWING! Adieu 2024!","url":"https://docs.google.com/forms/d/e/1FAIpQLSduL32P063F2f8dSkWvdxReZdWLlOlaVrs1j709RQudYwANIQ/viewform?usp=send_form","home":null,"check_url":"https://docs.google.com/spreadsheets/d/e/2PACX-1vQbhdLH5wXTHc0pwDxD8v3mAnCW6W_lfG-qRU8qdTvO7bwxNjpWFnBnHczfqamunU7BJL9wLch-qa_m/pubhtml","start_date":"2024-12-31","end_date":null,"dday":"종료","member_heart_count":0,"member_heart":[],"photo":"https://0-100.notion.site/image/https%3A%2F%2Fprod-files-secure.s3.us-west-2.amazonaws.com%2F4c8dfa27-59ce-4f93-855c-c41107b371d7%2F5e4429e1-b4fa-4fbd-8eb3-a963d7322d55%2FKakaoTalk_Photo_2024-11-15-20-36-24.png%3FX-Amz-Algorithm%3DAWS4-HMAC-SHA256%26X-Amz-Content-Sha256%3DUNSIGNED-PAYLOAD%26X-Amz-Credential%3DAKIAT73L2G45FSPPWI6X%252F20250119%252Fus-west-2%252Fs3%252Faws4_request%26X-Amz-Date%3D20250119T054224Z%26X-Amz-Expires%3D3600%26X-Amz-Signature%3D535ae95b9a7b9901006245790ed8872e5e4444d76044c2fb8d75aa523a9df03e%26X-Amz-SignedHeaders%3Dhost%26x-id%3DGetObject?cache=v2&table=block&id=143a94ce-1d13-80b3-8503-db45dd6fa8a9","created_time":"2024-11-19T14:29:00.000Z","last_modified_time":"2024-11-20T14:26:00.000Z"},{"page_id":"13ea94ce-1d13-8024-84be-c4c254d3bd1a","classification":"행사","year":2024,"name":"Take the s'A'voy Train to 2025 Party Registration","url":"https://forms.gle/vzPLoSe4aKgTQXFo9","home":null,"check_url":"https://docs.google.com/spreadsheets/d/e/2PACX-1vQgYm7sJBR88QN7QNVxP1C4vBq_knjKXuCzd63him7HaPbkp9FUbksaI9x-_eWFLRs7B1LggTbso6mV/pubhtml?gid=178698390&single=true","start_date":"2024-12-31","end_date":null,"dday":"종료","member_heart_count":0,"member_heart":[],"photo":"https://0-100.notion.site/image/https%3A%2F%2Fprod-files-secure.s3.us-west-2.amazonaws.com%2F4c8dfa27-59ce-4f93-855c-c41107b371d7%2F0810ea6a-f6e0-4f7f-8976-ce6a0757f652%2F241029_2025%25EC%2582%25AC%25EB%25B3%25B4%25EC%259D%25B4%25EB%25B3%25BC%25EB%25A3%25B8%25EC%2599%2584%25ED%2596%2589%25EC%2597%25B4%25EC%25B0%25A8_%25EC%259D%25B8%25EC%258A%25A4%25ED%2583%2580-01.jpg%3FX-Amz-Algorithm%3DAWS4-HMAC-SHA256%26X-Amz-Content-Sha256%3DUNSIGNED-PAYLOAD%26X-Amz-Credential%3DAKIAT73L2G45FSPPWI6X%252F20250119%252Fus-west-2%252Fs3%252Faws4_request%26X-Amz-Date%3D20250119T054224Z%26X-Amz-Expires%3D3600%26X-Amz-Signature%3De5b21130dde0effc7c48c73d7865cbfac7546170befab9dde1d2a6e337989df4%26X-Amz-SignedHeaders%3Dhost%26x-id%3DGetObject?cache=v2&table=block&id=13ea94ce-1d13-8024-84be-c4c254d3bd1a","created_time":"2024-11-14T14:49:00.000Z","last_modified_time":"2024-11-14T14:52:00.000Z"},{"page_id":"13ea94ce-1d13-80a5-87e6-def7b63cdcd4","classification":"행사","year":2024,"name":"Happy NEW TIME BALL 2024","url":"https://docs.google.com/forms/d/e/1FAIpQLSdvRZ1wzWcZF1zCZoB5tbMjPLhNhglWpL_r8xo76tHZ743Ukw/viewform","home":"https://www.swingxswing.net/","check_url":"https://docs.google.com/spreadsheets/d/1G5QNWkyAgACgMUFzfgbvQxyHr1rA4ODABfvOVqJS610/edit?gid=1530933121#gid=1530933121","start_date":"2024-12-31","end_date":"2025-01-01","dday":"종료","member_heart_count":0,"member_heart":[],"photo":"https://0-100.notion.site/image/https%3A%2F%2Fprod-files-secure.s3.us-west-2.amazonaws.com%2F4c8dfa27-59ce-4f93-855c-c41107b371d7%2Fc29c42b7-aa60-4fe2-a5e1-0960ce9f0280%2F002.jpg%3FX-Amz-Algorithm%3DAWS4-HMAC-SHA256%26X-Amz-Content-Sha256%3DUNSIGNED-PAYLOAD%26X-Amz-Credential%3DAKIAT73L2G45FSPPWI6X%252F20250119%252Fus-west-2%252Fs3%252Faws4_request%26X-Amz-Date%3D20250119T054224Z%26X-Amz-Expires%3D3600%26X-Amz-Signature%3Daf8541c399b5f468598fe06a3007ea288b85d78ba15f4518ee3edc2235e67301%26X-Amz-SignedHeaders%3Dhost%26x-id%3DGetObject?cache=v2&table=block&id=13ea94ce-1d13-80a5-87e6-def7b63cdcd4","created_time":"2024-11-14T14:37:00.000Z","last_modified_time":"2024-12-04T08:42:00.000Z"},{"page_id":"12da94ce-1d13-8042-bc74-e556fbb040bd","classification":"행사","year":2024,"name":"2024 Lindy Actually Party","url":"https://docs.google.com/forms/d/e/1FAIpQLSeYz3RKagxAlSy1tWjn7f-MVkmuZJ0BuIflEBOGeB7pFtQnYg/closedform","home":null,"check_url":"https://buly.kr/7x5BQZZ","start_date":"2024-12-20","end_date":null,"dday":"종료","member_heart_count":0,"member_heart":[],"photo":"https://0-100.notion.site/image/https%3A%2F%2Fprod-files-secure.s3.us-west-2.amazonaws.com%2F4c8dfa27-59ce-4f93-855c-c41107b371d7%2Fda66d30f-125a-40b4-b513-6373b3079f1d%2Fparty_poster.jpg%3FX-Amz-Algorithm%3DAWS4-HMAC-SHA256%26X-Amz-Content-Sha256%3DUNSIGNED-PAYLOAD%26X-Amz-Credential%3DAKIAT73L2G45FSPPWI6X%252F20250119%252Fus-west-2%252Fs3%252Faws4_request%26X-Amz-Date%3D20250119T054224Z%26X-Amz-Expires%3D3600%26X-Amz-Signature%3D659655c70c086c62a06863ed4856775145c20fe8a1edb6625dfbbe7196f95442%26X-Amz-SignedHeaders%3Dhost%26x-id%3DGetObject?cache=v2&table=block&id=12da94ce-1d13-8042-bc74-e556fbb040bd","created_time":"2024-10-28T13:49:00.000Z","last_modified_time":"2024-11-01T22:00:00.000Z"},{"page_id":"13da94ce-1d13-806f-ba1c-d407e043d465","classification":"행사","year":2024,"name":"2024 디제이 배틀 파티 신청","url":"https://docs.google.com/forms/d/1JBbdrM5pxrmq9FB_Ev3_19tP6M4_U6oJbGsaWUxgGDc/viewform?edit_requested=true","home":null,"check_url":null,"start_date":"2024-12-14","end_date":null,"dday":"종료","member_heart_count":0,"member_heart":[],"created_time":"2024-11-13T10:07:00.000Z","last_modified_time":"2024-11-13T10:09:00.000Z"},{"page_id":"13ba94ce-1d13-8054-a784-c72924b2ddfb","classification":"행사","year":2024,"name":"24.11.20.수 The Bigapple 이사 1st 앵콜~","url":"https://bit.ly/3NlgbpR","home":null,"check_url":"https://bit.ly/3Y1ZapE","start_date":"2024-11-20","end_date":null,"dday":"종료","member_heart_count":0,"member_heart":[],"photo":"https://0-100.notion.site/image/https%3A%2F%2Fprod-files-secure.s3.us-west-2.amazonaws.com%2F4c8dfa27-59ce-4f93-855c-c41107b371d7%2F9ee4ecbc-8276-4cd3-98d3-a3964dee7af5%2F20241103_162445.jpg%3FX-Amz-Algorithm%3DAWS4-HMAC-SHA256%26X-Amz-Content-Sha256%3DUNSIGNED-PAYLOAD%26X-Amz-Credential%3DAKIAT73L2G45FSPPWI6X%252F20250119%252Fus-west-2%252Fs3%252Faws4_request%26X-Amz-Date%3D20250119T054224Z%26X-Amz-Expires%3D3600%26X-Amz-Signature%3D20624de6fa2e35dc43f514d2830eefd6717aa8c9d353698b8e8b7f1c97cf0a78%26X-Amz-SignedHeaders%3Dhost%26x-id%3DGetObject?cache=v2&table=block&id=13ba94ce-1d13-8054-a784-c72924b2ddfb","created_time":"2024-11-11T13:56:00.000Z","last_modified_time":"2024-11-11T13:58:00.000Z"},{"page_id":"66a03d90-7a31-4305-996b-23991821c19e","classification":"행사","year":2024,"name":"[청주 골든스윙] 할로윈 파티일정(1차 안내)","url":null,"home":"https://cafe.naver.com/swingfriends/44733","check_url":null,"start_date":"2024-10-25","end_date":"2024-10-26","dday":"종료","member_heart_count":0,"member_heart":[],"photo":"https://0-100.notion.site/image/https%3A%2F%2Fprod-files-secure.s3.us-west-2.amazonaws.com%2F4c8dfa27-59ce-4f93-855c-c41107b371d7%2F77d5e440-5f9a-4172-9726-2fa568a7f8fa%2F24_%25EA%25B3%25A8%25EB%2593%25A0%25EC%258A%25A4%25EC%259C%2599_%25ED%2595%25A0%25EB%25A1%259C%25EC%259C%2588%25ED%258C%258C%25ED%258B%25B0_%25ED%258F%25AC%25EC%258A%25A4%25ED%2584%25B02.png%3FX-Amz-Algorithm%3DAWS4-HMAC-SHA256%26X-Amz-Content-Sha256%3DUNSIGNED-PAYLOAD%26X-Amz-Credential%3DAKIAT73L2G45FSPPWI6X%252F20250119%252Fus-west-2%252Fs3%252Faws4_request%26X-Amz-Date%3D20250119T054224Z%26X-Amz-Expires%3D3600%26X-Amz-Signature%3De52dfb3a17d4c0a2f39beec07ef568e0352d1ec61496b5741c396e90bdbae982%26X-Amz-SignedHeaders%3Dhost%26x-id%3DGetObject?cache=v2&table=block&id=66a03d90-7a31-4305-996b-23991821c19e","created_time":"2024-08-01T17:22:00.000Z","last_modified_time":"2024-08-01T17:25:00.000Z"},{"page_id":"41386927-82ee-4d47-80e3-78a22b42f6d4","classification":"행사","year":2024,"name":"Jump To Berlin","url":"https://docs.google.com/forms/d/e/1FAIpQLSfSlWCZJIxET7n4DFFX6ET6gF-KWO8sKv71HvfdB-GzwhsHYA/viewform","home":null,"check_url":null,"start_date":"2024-10-18","end_date":"2024-10-20","dday":"종료","member_heart_count":1,"member_heart":[{"id":"6236f4d9-a7bc-4afc-9c0b-a6c7f5ef3bc8"}],"photo":"https://0-100.notion.site/image/https%3A%2F%2Fprod-files-secure.s3.us-west-2.amazonaws.com%2F4c8dfa27-59ce-4f93-855c-c41107b371d7%2Fdb87a676-3edb-407d-a0ac-11c13e5a580f%2FJump_To_Berlin.png%3FX-Amz-Algorithm%3DAWS4-HMAC-SHA256%26X-Amz-Content-Sha256%3DUNSIGNED-PAYLOAD%26X-Amz-Credential%3DAKIAT73L2G45FSPPWI6X%252F20250119%252Fus-west-2%252Fs3%252Faws4_request%26X-Amz-Date%3D20250119T054224Z%26X-Amz-Expires%3D3600%26X-Amz-Signature%3D4dc0eaf7723fd929adac9bf5a291e45de83c1bdb0587226287aedee6d673757c%26X-Amz-SignedHeaders%3Dhost%26x-id%3DGetObject?cache=v2&table=block&id=41386927-82ee-4d47-80e3-78a22b42f6d4","created_time":"2024-08-13T13:55:00.000Z","last_modified_time":"2024-08-13T14:05:00.000Z"},{"page_id":"115a94ce-1d13-804e-b99e-c24b1c72252c","classification":"행사","year":2024,"name":"한글날 쓰윙큰잔치","url":"https://forms.gle/vS9qn1cFZCGSDdj69","home":null,"check_url":null,"start_date":"2024-10-09","end_date":null,"dday":"종료","member_heart_count":0,"member_heart":[],"photo":"https://0-100.notion.site/image/https%3A%2F%2Fprod-files-secure.s3.us-west-2.amazonaws.com%2F4c8dfa27-59ce-4f93-855c-c41107b371d7%2F34b8ee65-0fb5-4db8-938e-d86da6da4455%2F%25EC%2593%25B0%25EC%259C%2599%25ED%2581%25B0%25EC%259E%2594%25EC%25B9%2598_%25ED%258F%25AC%25EC%258A%25A4%25ED%2584%25B01.png%3FX-Amz-Algorithm%3DAWS4-HMAC-SHA256%26X-Amz-Content-Sha256%3DUNSIGNED-PAYLOAD%26X-Amz-Credential%3DAKIAT73L2G45FSPPWI6X%252F20250119%252Fus-west-2%252Fs3%252Faws4_request%26X-Amz-Date%3D20250119T054224Z%26X-Amz-Expires%3D3600%26X-Amz-Signature%3D51d066f7a2c4d3001e58a8a6cbca6e65f168ea68d06e82a15c730fbfc5b20067%26X-Amz-SignedHeaders%3Dhost%26x-id%3DGetObject?cache=v2&table=block&id=115a94ce-1d13-804e-b99e-c24b1c72252c","created_time":"2024-10-04T09:04:00.000Z","last_modified_time":"2024-10-04T09:09:00.000Z"},{"page_id":"106a94ce-1d13-80b9-8d8c-e10f586b4ac0","classification":"행사","year":2024,"name":"소소소: 소셜클럽에서 펼쳐지는 소소한 라이브 ","url":null,"home":null,"check_url":null,"start_date":"2024-10-05","end_date":null,"dday":"종료","member_heart_count":0,"member_heart":[],"photo":"https://0-100.notion.site/image/https%3A%2F%2Fprod-files-secure.s3.us-west-2.amazonaws.com%2F4c8dfa27-59ce-4f93-855c-c41107b371d7%2F17efeaee-2b7e-4e86-8c27-e83578bf546d%2F%25EC%2586%258C%25EC%2586%258C%25ED%2595%259C_%25EC%2586%258C%25EC%2585%259C%25ED%2581%25B4%25EB%259F%25BD_%25EB%259D%25BC%25EC%259D%25B4%25EB%25B8%258C.jpg%3FX-Amz-Algorithm%3DAWS4-HMAC-SHA256%26X-Amz-Content-Sha256%3DUNSIGNED-PAYLOAD%26X-Amz-Credential%3DAKIAT73L2G45FSPPWI6X%252F20250119%252Fus-west-2%252Fs3%252Faws4_request%26X-Amz-Date%3D20250119T054224Z%26X-Amz-Expires%3D3600%26X-Amz-Signature%3D6279c3156f1ef3198373a7d85af6ae6ae2ef9ac8e3c4c84b185ae62ec8f9dd7a%26X-Amz-SignedHeaders%3Dhost%26x-id%3DGetObject?cache=v2&table=block&id=106a94ce-1d13-80b9-8d8c-e10f586b4ac0","created_time":"2024-09-19T16:45:00.000Z","last_modified_time":"2024-09-19T16:47:00.000Z"},{"page_id":"5c67a5a7-89a7-4cb2-86ca-4363b4531bab","classification":"행사","year":2024,"name":"아무나 와. 그냥 춰! with Swing Friends!","url":"https://url.kr/vx2zkh","home":null,"check_url":"https://docs.google.com/spreadsheets/d/12OtgW5mR2qi-OqHxwstDSAtLfxVz5zmEQi7ta2-mnTc/edit?resourcekey=&gid=1518487024#gid=1518487024","start_date":"2024-08-31","end_date":null,"dday":"종료","member_heart_count":0,"member_heart":[],"photo":"https://0-100.notion.site/image/https%3A%2F%2Fprod-files-secure.s3.us-west-2.amazonaws.com%2F4c8dfa27-59ce-4f93-855c-c41107b371d7%2F66903136-3e23-4a08-8cef-02462aec2dbb%2F%25EB%25B2%25BD%25EC%25A7%2580_%25EC%25B5%259C%25EC%25A2%2585.jpg%3FX-Amz-Algorithm%3DAWS4-HMAC-SHA256%26X-Amz-Content-Sha256%3DUNSIGNED-PAYLOAD%26X-Amz-Credential%3DAKIAT73L2G45FSPPWI6X%252F20250119%252Fus-west-2%252Fs3%252Faws4_request%26X-Amz-Date%3D20250119T054224Z%26X-Amz-Expires%3D3600%26X-Amz-Signature%3D5866b64f99457037ed01d1f9a9db0ef67da2c4bc281f9934c77d78c124384f14%26X-Amz-SignedHeaders%3Dhost%26x-id%3DGetObject?cache=v2&table=block&id=5c67a5a7-89a7-4cb2-86ca-4363b4531bab","created_time":"2024-08-07T14:24:00.000Z","last_modified_time":"2024-08-18T10:08:00.000Z"},{"page_id":"2b71cb34-6c88-43e9-bf21-75c3734785b1","classification":"행사","year":2024,"name":"제 1회 스윙타운 Live&졸업파티 신청서","url":"https://docs.google.com/forms/d/e/1FAIpQLSdYhM0SURRkPN-5s4p_tr6PLcOcTQNS8rnYOFAGZI3IhSCCHw/viewform","home":null,"check_url":"https://docs.google.com/spreadsheets/d/1lVGZhtuCsZF1QlRixsR3JZ57hfhcJMXxTk99AAnv11I/edit?gid=0#gid=0","start_date":"2024-08-24","end_date":null,"dday":"종료","member_heart_count":0,"member_heart":[],"photo":"https://0-100.notion.site/image/https%3A%2F%2Fprod-files-secure.s3.us-west-2.amazonaws.com%2F4c8dfa27-59ce-4f93-855c-c41107b371d7%2Fb1c1f274-3ab5-4379-be46-50773ad45a81%2F%25EC%25A1%25B8%25EC%2597%2585%25ED%258C%258C%25ED%258B%25B0_%25ED%258F%25AC%25EC%258A%25A4%25ED%2584%25B0%2528%25EC%25A0%2595%25EC%2582%25AC%25EA%25B0%2581%25ED%2598%2595%2529.png%3FX-Amz-Algorithm%3DAWS4-HMAC-SHA256%26X-Amz-Content-Sha256%3DUNSIGNED-PAYLOAD%26X-Amz-Credential%3DAKIAT73L2G45FSPPWI6X%252F20250119%252Fus-west-2%252Fs3%252Faws4_request%26X-Amz-Date%3D20250119T054224Z%26X-Amz-Expires%3D3600%26X-Amz-Signature%3Da475de14e403f421503fbb7ec8f3103e0e13913eaff9e2962c12146a6c909fa6%26X-Amz-SignedHeaders%3Dhost%26x-id%3DGetObject?cache=v2&table=block&id=2b71cb34-6c88-43e9-bf21-75c3734785b1","created_time":"2024-08-23T08:39:00.000Z","last_modified_time":"2024-08-23T08:43:00.000Z"},{"page_id":"e7994c77-4f88-4be2-8e36-d2b07ecc9931","classification":"행사","year":2024,"name":"RHYTHM & BLUES - night : BUSAN","url":"https://docs.google.com/forms/d/e/1FAIpQLSfCe5h84tYG7NMOCYmUvSlFRhc0UtAQE-tyMvpkIZ59ncE1Bg/viewform","home":"https://pushy-rat-533.notion.site/8-24-38ca0f80eb31406e90ea67493a71a7a4","check_url":"https://docs.google.com/spreadsheets/d/1FO6e8SCT_S7hNRLFhzRWy1iAV8ySJcfVKWahSnGl0kE/edit?gid=0#gid=0","start_date":"2024-08-24","end_date":null,"dday":"종료","member_heart_count":0,"member_heart":[],"photo":"https://0-100.notion.site/image/https%3A%2F%2Fprod-files-secure.s3.us-west-2.amazonaws.com%2F4c8dfa27-59ce-4f93-855c-c41107b371d7%2Fcf9a1072-8aa3-4db3-a885-2ff678f43964%2F%25EB%25B6%2580%25EC%2582%25B0_%25EB%25A6%25AC%25EC%2595%25A4%25EB%25B8%2594.jpg%3FX-Amz-Algorithm%3DAWS4-HMAC-SHA256%26X-Amz-Content-Sha256%3DUNSIGNED-PAYLOAD%26X-Amz-Credential%3DAKIAT73L2G45FSPPWI6X%252F20250119%252Fus-west-2%252Fs3%252Faws4_request%26X-Amz-Date%3D20250119T054224Z%26X-Amz-Expires%3D3600%26X-Amz-Signature%3D0f917d58b5c6984f1a7ff21bfdce6a664c6c1598c181a15750068fc7633adb3a%26X-Amz-SignedHeaders%3Dhost%26x-id%3DGetObject?cache=v2&table=block&id=e7994c77-4f88-4be2-8e36-d2b07ecc9931","created_time":"2024-07-10T17:28:00.000Z","last_modified_time":"2024-07-10T17:34:00.000Z"},{"page_id":"b2cf7e44-d98c-40ae-9f16-f179daa45cd3","classification":"행사","year":2024,"name":"JAZZ CATS  아직 놀NIGHT","url":"https://forms.gle/9yNhxXAJ1Bs97fgs6","home":null,"check_url":"https://zrr.kr/eZCt","start_date":"2024-08-15","end_date":null,"dday":"종료","member_heart_count":0,"member_heart":[],"photo":"https://0-100.notion.site/image/https%3A%2F%2Fprod-files-secure.s3.us-west-2.amazonaws.com%2F4c8dfa27-59ce-4f93-855c-c41107b371d7%2Ffcaedc56-91ad-4f2a-b421-a83c8ba9df75%2F%25E1%2584%258C%25E1%2585%25A2%25E1%2584%258C%25E1%2585%25B3%25E1%2584%258F%25E1%2585%25A2%25E1%2586%25BA%25E1%2584%258E%25E1%2585%25B3_%25281%2529.jpg%3FX-Amz-Algorithm%3DAWS4-HMAC-SHA256%26X-Amz-Content-Sha256%3DUNSIGNED-PAYLOAD%26X-Amz-Credential%3DAKIAT73L2G45FSPPWI6X%252F20250119%252Fus-west-2%252Fs3%252Faws4_request%26X-Amz-Date%3D20250119T054224Z%26X-Amz-Expires%3D3600%26X-Amz-Signature%3D96d560dd04bc9fbdfe8ef67e19280a315abe8c0f8550b15ce1fc45be42d6cf95%26X-Amz-SignedHeaders%3Dhost%26x-id%3DGetObject?cache=v2&table=block&id=b2cf7e44-d98c-40ae-9f16-f179daa45cd3","created_time":"2024-06-25T11:38:00.000Z","last_modified_time":"2024-06-27T11:32:00.000Z"},{"page_id":"e6ec701f-0057-4423-9f54-329256394ced","classification":"행사","year":2024,"name":"해피♥라이브 #4 Sage Min Swingtet","url":"https://m.site.naver.com/1r88O","home":null,"check_url":"https://m.site.naver.com/1r8ar","start_date":"2024-08-14","end_date":null,"dday":"종료","member_heart_count":0,"member_heart":[],"photo":"https://0-100.notion.site/image/https%3A%2F%2Fprod-files-secure.s3.us-west-2.amazonaws.com%2F4c8dfa27-59ce-4f93-855c-c41107b371d7%2F557ae011-9a5e-4636-a359-26231e748d4b%2F%25ED%2595%25B4%25ED%2594%25BC%25EB%259D%25BC%25EC%259D%25B4%25EB%25B8%258C4.jpg%3FX-Amz-Algorithm%3DAWS4-HMAC-SHA256%26X-Amz-Content-Sha256%3DUNSIGNED-PAYLOAD%26X-Amz-Credential%3DAKIAT73L2G45FSPPWI6X%252F20250119%252Fus-west-2%252Fs3%252Faws4_request%26X-Amz-Date%3D20250119T054224Z%26X-Amz-Expires%3D3600%26X-Amz-Signature%3D49b59099429d56b9c56d662898f9f6b5ec287ce2d8ea4c98b321fae3daa02b9f%26X-Amz-SignedHeaders%3Dhost%26x-id%3DGetObject?cache=v2&table=block&id=e6ec701f-0057-4423-9f54-329256394ced","created_time":"2024-08-12T16:19:00.000Z","last_modified_time":"2024-08-13T14:05:00.000Z"},{"page_id":"36f0219e-aab1-442e-97b6-a419230eb06c","classification":"행사","year":2024,"name":"굴다리 Holiday","url":"https://docs.google.com/forms/d/e/1FAIpQLSe0FctmeUAEjh_Sp8fXtygcufIl6KrRThCvhpgAAIT4fdY05w/closedform","home":"https://linktr.ee/GSC.SWING","check_url":"https://docs.google.com/spreadsheets/d/1ALaUuCsk8ZKlg0msXw5iXp6M4_bqYVaUZKAlp_vlhBg/edit?resourcekey=&gid=287676571#gid=287676571","start_date":"2024-08-14","end_date":null,"dday":"종료","member_heart_count":0,"member_heart":[],"created_time":"2024-07-23T15:54:00.000Z","last_modified_time":"2024-07-23T15:59:00.000Z"},{"page_id":"5d9972f1-93e4-4c2d-91d8-ec268582e6eb","classification":"행사","year":2024,"name":"Jeju Swing Camp 제주스윙캠프","url":null,"home":"https://www.facebook.com/Jejuswing/?locale=ko_KR","check_url":null,"start_date":"2024-07-12","end_date":"2024-07-14","dday":"종료","member_heart_count":0,"member_heart":[],"photo":"https://0-100.notion.site/image/https%3A%2F%2Fprod-files-secure.s3.us-west-2.amazonaws.com%2F4c8dfa27-59ce-4f93-855c-c41107b371d7%2Fbb29d978-05e8-4dc2-a19d-7c4a3e1970a1%2F370922859_761203059347111_9021262375220005353_n.jpg%3FX-Amz-Algorithm%3DAWS4-HMAC-SHA256%26X-Amz-Content-Sha256%3DUNSIGNED-PAYLOAD%26X-Amz-Credential%3DAKIAT73L2G45FSPPWI6X%252F20250119%252Fus-west-2%252Fs3%252Faws4_request%26X-Amz-Date%3D20250119T054224Z%26X-Amz-Expires%3D3600%26X-Amz-Signature%3Dd5ad934bf8cddffecaf1c525d1d78854792808ad53cd7e6ada2dab1777e63d02%26X-Amz-SignedHeaders%3Dhost%26x-id%3DGetObject?cache=v2&table=block&id=5d9972f1-93e4-4c2d-91d8-ec268582e6eb","created_time":"2024-07-10T12:42:00.000Z","last_modified_time":"2024-07-10T17:03:00.000Z"},{"page_id":"13eb0c32-3129-4608-b68d-8a6633503030","classification":"행사","year":2024,"name":"Swingin' at the SAVOY 2024 #2","url":"https://forms.gle/w3Wak59xASjprQZEA","home":null,"check_url":"https://bit.ly/3x2gzoz","start_date":"2024-07-07","end_date":null,"dday":"종료","member_heart_count":0,"member_heart":[],"photo":"https://0-100.notion.site/image/https%3A%2F%2Fprod-files-secure.s3.us-west-2.amazonaws.com%2F4c8dfa27-59ce-4f93-855c-c41107b371d7%2Fbce640e3-b00a-48a3-ac71-f3b3a3518699%2FSwingin_at_the_SAVOY_2024_2.png%3FX-Amz-Algorithm%3DAWS4-HMAC-SHA256%26X-Amz-Content-Sha256%3DUNSIGNED-PAYLOAD%26X-Amz-Credential%3DAKIAT73L2G45FSPPWI6X%252F20250119%252Fus-west-2%252Fs3%252Faws4_request%26X-Amz-Date%3D20250119T054224Z%26X-Amz-Expires%3D3600%26X-Amz-Signature%3D1f75caf5cd298a765919718cfe7a4afd6f5b32846daecc94dc8398661ffa80f9%26X-Amz-SignedHeaders%3Dhost%26x-id%3DGetObject?cache=v2&table=block&id=13eb0c32-3129-4608-b68d-8a6633503030","created_time":"2024-07-08T12:51:00.000Z","last_modified_time":"2024-07-08T12:53:00.000Z"},{"page_id":"03604354-7333-484a-9760-e3337406d073","classification":"행사","year":2024,"name":"스윙프렌즈 MT","url":"https://forms.gle/9JnvrihVz5JSdtPW9","home":"https://cafe.naver.com/swingfriends/43673","check_url":null,"start_date":"2024-06-29","end_date":"2024-06-30","dday":"종료","member_heart_count":0,"member_heart":[],"photo":"https://0-100.notion.site/image/https%3A%2F%2Fprod-files-secure.s3.us-west-2.amazonaws.com%2F4c8dfa27-59ce-4f93-855c-c41107b371d7%2F95030357-ffab-4d8d-9b82-5dcb0d5de0d3%2F%25E1%2584%2589%25E1%2585%25B3%25E1%2584%258B%25E1%2585%25B1%25E1%2586%25BC%25E1%2584%2591%25E1%2585%25B3%25E1%2584%2585%25E1%2585%25A6%25E1%2586%25AB%25E1%2584%258C%25E1%2585%25B3_2024_%25E1%2584%258B%25E1%2585%25A6%25E1%2586%25B7%25E1%2584%2590%25E1%2585%25B5_%25E1%2584%2591%25E1%2585%25A9%25E1%2584%2589%25E1%2585%25B3%25E1%2584%2590%25E1%2585%25A5.webp%3FX-Amz-Algorithm%3DAWS4-HMAC-SHA256%26X-Amz-Content-Sha256%3DUNSIGNED-PAYLOAD%26X-Amz-Credential%3DAKIAT73L2G45FSPPWI6X%252F20250119%252Fus-west-2%252Fs3%252Faws4_request%26X-Amz-Date%3D20250119T054224Z%26X-Amz-Expires%3D3600%26X-Amz-Signature%3Da58795a38374c69153c1d86e622df55b70819f5f7f4b85a71a07b3d375e21da8%26X-Amz-SignedHeaders%3Dhost%26x-id%3DGetObject?cache=v2&table=block&id=03604354-7333-484a-9760-e3337406d073","created_time":"2024-05-13T17:31:00.000Z","last_modified_time":"2024-06-03T02:01:00.000Z"},{"page_id":"f1e6504a-4191-40b1-aa37-ec43b084c4c4","classification":"행사","year":2024,"name":"리듬코리아","url":"https://rhythmk.com/rk2024","home":"https://www.rhythmkorea.com","check_url":"https://rhythmk.com/rk2024c","start_date":"2024-06-21","end_date":"2024-06-23","dday":"종료","member_heart_count":0,"member_heart":[],"photo":"https://0-100.notion.site/image/https%3A%2F%2Fprod-files-secure.s3.us-west-2.amazonaws.com%2F4c8dfa27-59ce-4f93-855c-c41107b371d7%2F98595b25-1677-4f2c-91b1-72bc9ce31d2e%2FRK-2024-Poster.webp%3FX-Amz-Algorithm%3DAWS4-HMAC-SHA256%26X-Amz-Content-Sha256%3DUNSIGNED-PAYLOAD%26X-Amz-Credential%3DAKIAT73L2G45FSPPWI6X%252F20250119%252Fus-west-2%252Fs3%252Faws4_request%26X-Amz-Date%3D20250119T054224Z%26X-Amz-Expires%3D3600%26X-Amz-Signature%3D923cfa43464087eafa979ef9ce61b4d0fa57dc6db01e70d6675436de84b89000%26X-Amz-SignedHeaders%3Dhost%26x-id%3DGetObject?cache=v2&table=block&id=f1e6504a-4191-40b1-aa37-ec43b084c4c4","created_time":"2024-04-20T23:58:00.000Z","last_modified_time":"2024-05-27T00:01:00.000Z"}]